splinepy/__init__.py
splinepy/_base.py
splinepy/_version.py
splinepy/bezier.py
splinepy/bspline.py
splinepy/cli.py
splinepy/helpme/__init__.py
splinepy/helpme/check.py
splinepy/helpme/create.py
splinepy/helpme/extract.py
splinepy/helpme/ffd.py
splinepy/helpme/fit.py
splinepy/helpme/integrate.py
splinepy/helpme/mapper.py
splinepy/helpme/multi_index.py
splinepy/helpme/reparametrize.py
splinepy/helpme/visualize.py
splinepy/io/__init__.py
splinepy/io/cats.py
splinepy/io/default.py
splinepy/io/gismo.py
splinepy/io/iges.py
splinepy/io/ioutils.py
splinepy/io/irit.py
splinepy/io/json.py
splinepy/io/mfem.py
splinepy/io/npz.py
splinepy/io/svg.py
splinepy/microstructure/__init__.py
splinepy/microstructure/microstructure.py
splinepy/microstructure/tiles/__init__.py
splinepy/microstructure/tiles/armadillo.py
splinepy/microstructure/tiles/chi.py
splinepy/microstructure/tiles/cross_2d.py
splinepy/microstructure/tiles/cross_3d.py
splinepy/microstructure/tiles/cross_3d_linear.py
splinepy/microstructure/tiles/cube_void.py
splinepy/microstructure/tiles/double_lattice.py
splinepy/microstructure/tiles/ellips_v_oid.py
splinepy/microstructure/tiles/hollow_cube.py
splinepy/microstructure/tiles/hollow_octagon.py
splinepy/microstructure/tiles/hollow_octagon_extrude.py
splinepy/microstructure/tiles/inverse_cross_3d.py
splinepy/microstructure/tiles/snappy.py
splinepy/microstructure/tiles/tile_base.py
splinepy/multipatch.py
splinepy/nurbs.py
splinepy/rational_bezier.py
splinepy/settings.py
splinepy/spline.py
splinepy/splinepy_core.cp313-win_amd64.pyd
splinepy/utils/__init__.py
splinepy/utils/data.py
splinepy/utils/log.py
splinepy-0.2.0.dist-info/METADATA
splinepy-0.2.0.dist-info/WHEEL
splinepy-0.2.0.dist-info/entry_points.txt
splinepy-0.2.0.dist-info/licenses/LICENSE
splinepy-0.2.0.dist-info/RECORD
