Metadata-Version: 2.2
Name: splinepy
Version: 0.2.0
Summary: Library for prototyping spline geometries of arbitrary dimensions and degrees, and IGA
Keywords: bezier,rational bezier,bspline,nurbs,multi patch
Author-Email: Jaewook Lee <jaewooklee042@gmail.com>
License: MIT License
Classifier: Development Status :: 4 - Beta
Classifier: License :: OSI Approved :: MIT License
Classifier: Programming Language :: Python
Classifier: Programming Language :: Python :: 3.9
Classifier: Programming Language :: Python :: 3.10
Classifier: Programming Language :: Python :: 3.11
Classifier: Programming Language :: Python :: 3.12
Classifier: Programming Language :: Python :: 3.13
Classifier: Natural Language :: English
Classifier: Topic :: Scientific/Engineering
Project-URL: Homepage, https://github.com/tataratat/splinepy
Requires-Python: >=3.8
Requires-Dist: numpy
Requires-Dist: gustaf>=0.0.25
Provides-Extra: all
Requires-Dist: gustaf[all]>=0.0.25; extra == "all"
Provides-Extra: test
Requires-Dist: funi>=0.1.0; extra == "test"
Requires-Dist: pytest; extra == "test"
